Workbook

Sheet Use Cases
A1: Interaction | B1: Use Case | C1: Agentic Application | D1: Model Type | E1: Model Purpose | G1: Model Calls per Interaction | H1: Avg Input Tokens per Call | I1: Avg Output Tokens per Call | J1: Input $/1M (lookup) | K1: Output $/1M (lookup) | L1: Cost per Model Call | M1: Cost per Interaction | N1: Model Calls attributed to Interactions | O1: Unit Cost
A2: What did i spent on Dining Bill? | B2: Chat to my finances | C2: conversational-banking | D2: GPT-4.1 | E2: Reasoning | G2: 1 | H2: 5000 | I2: 1000 | J2: =IFERROR(VLOOKUP(D2,Models!$A:$D,3,FALSE),"") -> 2 | K2: =IFERROR(VLOOKUP(D2,Models!$A:$D,4,FALSE),"") -> 8 | L2: =IFERROR((H2/1000000)*J2+(I2/1000000)*K2,"") -> 0.018 | M2: =IFERROR(L2*G2,"") -> 0.018 | N2: 2 | O2: =IFERROR(M2*N2,"") -> 0.036
D3: text-embedding-3-small | E3: embedding | G3: 1 | H3: 10 | I3: 0 | J3: =IFERROR(VLOOKUP(D3,Models!$A:$D,3,FALSE),"") -> 0.025 | K3: 0 | L3: =IFERROR((H3/1000000)*J3+(I3/1000000)*K3,"") -> 2.5e-07 | M3: =IFERROR(L3*G3,"") -> 2.5e-07 | N3: 1 | O3: =IFERROR(M3*N3,"") -> 2.5e-07
D4: GPT-4o-mini | E4: Application Guardrails | G4: 1 | H4: 1200 | I4: 5 | J4: =IFERROR(VLOOKUP(D4,Models!$A:$D,3,FALSE),"") -> 0.15 | K4: =IFERROR(VLOOKUP(D4,Models!$A:$D,4,FALSE),"") -> 0.6 | L4: =IFERROR((H4/1000000)*J4+(I4/1000000)*K4,"") -> 0.000183 | M4: =IFERROR(L4*G4,"") -> 0.000183 | N4: 1 | O4: =IFERROR(M4*N4,"") -> 0.000183
D5: GPT-4.1-mini | E5: Online Evals | G5: 2 | H5: 750 | I5: 80 | J5: =IFERROR(VLOOKUP(D5,Models!$A:$D,3,FALSE),"") -> 0.4 | K5: =IFERROR(VLOOKUP(D5,Models!$A:$D,4,FALSE),"") -> 1.6 | L5: =IFERROR((H5/1000000)*J5+(I5/1000000)*K5,"") -> 0.000428 | M5: =IFERROR(L5*G5,"") -> 0.000856 | N5: 1 | O5: =IFERROR(M5*N5,"") -> 0.000856
N6: =SUM(N2:N5) -> 5 | O6: =SUM(O2:O5) -> 0.03703925
A7: Transfer 5$ to Tom | B7: Money Movement | C7: conversational-banking | D7: GPT-4.1 | E7: Tool Calling, Response Generation | G7: 2 | H7: 5800 | I7: 1000 | J7: =IFERROR(VLOOKUP(D7,Models!$A:$D,3,FALSE),"") -> 2 | K7: =IFERROR(VLOOKUP(D7,Models!$A:$D,4,FALSE),"") -> 8 | L7: =IFERROR((H7/1000000)*J7+(I7/1000000)*K7,"") -> 0.0196 | M7: =IFERROR(L7*G7,"") -> 0.0392 | N7: 1 | O7: =IFERROR(M7*N7,"") -> 0.0392
D8: GPT-4o-mini | E8: Application Guardrails | G8: 1 | H8: 2000 | I8: 5 | J8: =IFERROR(VLOOKUP(D8,Models!$A:$D,3,FALSE),"") -> 0.15 | K8: =IFERROR(VLOOKUP(D8,Models!$A:$D,4,FALSE),"") -> 0.6 | L8: =IFERROR((H8/1000000)*J8+(I8/1000000)*K8,"") -> 0.000303 | M8: =IFERROR(L8*G8,"") -> 0.000303 | N8: 1 | O8: =IFERROR(M8*N8,"") -> 0.000303
N10: =SUM(N7:N9) -> 2 | O10: =SUM(O7:O8) -> 0.039503
C15: Monthly Sessions | D15: 600000 | E15: Interaction Distribution in a Session | F15: # Models called | G15: Model Costs(Sessions*Interaction*Total Model cost per interaction)
D16: Chat with my Finances Interactions per session | E16: 2 | F16: =N6 -> 5 | G16: =D15*E16*O6 -> 44447.1
D17: Move money Interactions per session | E17: 1 | F17: =N10 -> 2 | G17: =D15*E17*O10 -> 23701.8
G19: =SUM(G16:G17) -> 68148.9
D24: Summary : If there are 600000 sessions a month and each sessions have 3 chats , we assume 2 are around chatting with finances and 1 is around money movement

Sheet Simulations
A1: Sessions in Current Month | B1: total average monthly model calls | C1: Monthly Model Cost (3 interactions per session) | D1: Annual Sessions | E1: Annual Model Cost | F1: with Yearly PTU | G1: Annual costs In millions | H1: Non-discounted Model cost per session (3 interactions) | I1: PTU Per session | J1: Non-discounted Model cost per interactions | K1: PTU Costs per interaction
A2: 600000 | B2: =A2*12 -> 7200000 | C2: =A2*(('Use Cases'!E16*'Use Cases'!O6)+('Use Cases'!E17*'Use Cases'!O10)) -> 68148.9 | D2: =A2*12 -> 7200000 | E2: =C2*12 -> 817786.8 | F2: =E2*0.45 -> 368004.06 | G2: =IFERROR(__xludf.DUMMYFUNCTION("AI(""express in millions"",E2)"),"$0.82 million") -> $0.82 million | H2: =E2/D2 -> 0.1135815 | I2: =H2*0.45 -> 0.051111675 | J2: =H2/3 -> 0.0378605 | K2: =J2*0.45 -> 0.017037225
A3: 1000000 | B3: =A3*12 -> 12000000 | C3: =A3*(('Use Cases'!E16*'Use Cases'!O6)+('Use Cases'!E17*'Use Cases'!O10)) -> 113581.5 | D3: =A3*12 -> 12000000 | E3: =C3*12 -> 1362978 | F3: =E3*0.45 -> 613340.1 | G3: =IFERROR(__xludf.DUMMYFUNCTION("AI(""express in millions"",E3)"),"$1.36 million") -> $1.36 million | H3: =E3/D3 -> 0.1135815 | I3: =H3*0.45 -> 0.051111675 | J3: =H3/3 -> 0.0378605 | K3: =J3*0.45 -> 0.017037225
A4: 5000000 | B4: =A4*12 -> 60000000 | C4: =A4*(('Use Cases'!E16*'Use Cases'!O6)+('Use Cases'!E17*'Use Cases'!O10)) -> 567907.5 | D4: =A4*12 -> 60000000 | E4: =C4*12 -> 6814890 | F4: =E4*0.45 -> 3066700.5 | G4: =IFERROR(__xludf.DUMMYFUNCTION("AI(""express in millions"",E4)"),"$6.81 million") -> $6.81 million | H4: =E4/D4 -> 0.1135815 | I4: =H4*0.45 -> 0.051111675 | J4: =H4/3 -> 0.0378605 | K4: =J4*0.45 -> 0.017037225
A5: 8000000 | B5: =A5*12 -> 96000000 | C5: =A5*(('Use Cases'!E16*'Use Cases'!O6)+('Use Cases'!E17*'Use Cases'!O10)) -> 908652 | D5: =A5*12 -> 96000000 | E5: =C5*12 -> 10903824 | F5: =E5*0.45 -> 4906720.8 | G5: =IFERROR(__xludf.DUMMYFUNCTION("AI(""express in millions"",E5)"),"$10.90 million") -> $10.90 million | H5: =E5/D5 -> 0.1135815 | I5: =H5*0.45 -> 0.051111675 | J5: =H5/3 -> 0.0378605 | K5: =J5*0.45 -> 0.017037225
A6: 10000000 | B6: =A6*12 -> 120000000 | C6: =A6*(('Use Cases'!E16*'Use Cases'!O6)+('Use Cases'!E17*'Use Cases'!O10)) -> 1135815 | D6: =A6*12 -> 120000000 | E6: =C6*12 -> 13629780 | F6: =E6*0.45 -> 6133401 | G6: =IFERROR(__xludf.DUMMYFUNCTION("AI(""express in millions"",E6)"),"$13.63 million") -> $13.63 million | H6: =E6/D6 -> 0.1135815 | I6: =H6*0.45 -> 0.051111675 | J6: =H6/3 -> 0.0378605 | K6: =J6*0.45 -> 0.017037225
A7: 15000000 | B7: =A7*12 -> 180000000 | C7: =A7*(('Use Cases'!E16*'Use Cases'!O6)+('Use Cases'!E17*'Use Cases'!O10)) -> 1703722.5 | D7: =A7*12 -> 180000000 | E7: =C7*12 -> 20444670 | F7: =E7*0.45 -> 9200101.5 | G7: =IFERROR(__xludf.DUMMYFUNCTION("AI(""express in millions"",E7)"),"$20.44 million") -> $20.44 million | H7: =E7/D7 -> 0.1135815 | I7: =H7*0.45 -> 0.051111675 | J7: =H7/3 -> 0.0378605 | K7: =J7*0.45 -> 0.017037225
B9: Pay as you Go | C9: PAYG with MACC Discount | D9: PTU Hourly | E9: PTU Monthly Reservation | F9: PTU Yearly Reservation
A10: Chat to my finances | B10: 44447 | C10: 35557 | D10: 75240 | E10: 2717 | F10: 23085
A11: Money Movement | B11: 23701 | C11: 18961 | D11: 23760 | E11: 8580 | F11: 7290
A12: Total | B12: 68148 | C12: 54519 | D12: 99000 | E12: 35750 | F12: 30375

Sheet Sheet5

Sheet Models
A1: Model Name | B1: Provider | C1: Input $/1M tokens | D1: Output $/1M tokens
A2: Claude 3.5 Sonnet | B2: Anthropic | C2: 3 | D2: 15
A3: Claude Sonnet 4 | B3: Anthropic | C3: 3 | D3: 15
A4: GPT-4.1 | B4: Azure AI Foundry | C4: 2 | D4: 8
A5: GPT-4.1-mini | B5: Azure AI Foundry | C5: 0.4 | D5: 1.6
A6: GPT-4.1-nano | B6: Azure AI Foundry | C6: 0.1 | D6: 0.4
A7: GPT-4o | B7: Azure AI Foundry | C7: 2.5 | D7: 10
A8: GPT-4o-mini | B8: Azure AI Foundry | C8: 0.15 | D8: 0.6
A9: GPT 5.1 | B9: Azure AI Foundry | C9: 1.06 | D9: 8.48
A10: GPT 5.2 | B10: Azure AI Foundry | C10: 1.49 | D10: 11.47
A11: o3 | B11: Azure AI Foundry | C11: 2 | D11: 8
A12: o4-mini | B12: Azure AI Foundry | C12: 1.1 | D12: 4.4
A13: text-embedding-3-small | B13: Azure AI Foundry | C13: 0.025

Sheet WIP BB Agentic Platform Costs
E1: Comments
A2: Sessions | B2: 5000000
A3: Interactions | B3: =B2*B4 -> 15000000
A4: Number of interactions per sessions | B4: 3
A5: LF Units | B5: =B3*7 -> 105000000 | E5: Per interactions, Langfuse consumes 7 LF units
A6: Number of Microservices running in DTAP | B6: 1 | E6: Depending on architecture, could run multiple agents in 1 MS, or 1:1 | working thesiss, making more microservcies running less agents, woud result in same costs structure as more MS will be able to run in a VM
A7: Autoscaling rate/1000 requests | B7: =I37 -> 0.0060013717
A10: Costs | B10: Type | C10: Type 2 | D10: Costs 2 | E10: Details
A11: Compute attributed to Agent (DTAP Base) | B11: Compute | C11: Per Agent | D11: =I32*B6 -> 326.66667 | E11: =IFERROR(__xludf.DUMMYFUNCTION("AI (""explain how this calculated"",H26:J32)"),"The cost of $326.67 is calculated by multiplying the number of base pods required for an agent across all environments (7 pods) by the cost per individual pod ($46.67). The specific components are: - Node costs: $140.00 - Pods per node: 3 - Cost per"&" pod: $140.00 / 3 = $46.67 - Base pods: 7 (comprised of 1 Dev, 2 Test/Staging, 3 Production, and 1 Disaster Recovery) - Total Calculation: 7 pods × $46.67 per pod = $326.67") -> The cost of $326.67 is calculated by multiplying the number of base pods required for an agent across all environments (7 pods) by the cost per individual pod ($46.67). The specific components are: - Node costs: $140.00 - Pods per node: 3 - Cost per pod: $140.00 / 3 = $46.67 - Base pods: 7 (comprised of 1 Dev, 2 Test/Staging, 3 Production, and 1 Disaster Recovery) - Total Calculation: 7 pods × $46.67 per pod = $326.67
A12: Agent Compute (Prod Request based autoscaling) | B12: Usage based compute | C12: Per 1K requests | D12: =B3/1000* B7 -> 90.020576 | E12: =IFERROR(__xludf.DUMMYFUNCTION("AI (""explain how this calculated"",H34:J37)"),"The autoscaling rate of $0.006001 per 1,000 requests is calculated using the following components: - Pod Cost: $46.00 per pod - Replicas: 3 pods (one for each availability zone to ensure redundancy) - Monthly Requests per Pod: 22,982,400 (derived fro"&"m 7,776,000 requests at 30% utilization, which implies a 100% capacity of 25,920,000, though the formula note specifically uses the relationship of 3 replicas to the throughput) - Calculation: (Total Cost of 3 Pods) / (Total Monthly Capacity in thousand"&"s of requests)Specifically, the formula 46 * 3 / 22,982.4 results in the rate of $0.006001. This ensures that while 3 replicas are run for redundancy, the cost is distributed across the total throughput provided by those pods.") -> The autoscaling rate of $0.006001 per 1,000 requests is calculated using the following components: - Pod Cost: $46.00 per pod - Replicas: 3 pods (one for each availability zone to ensure redundancy) - Monthly Requests per Pod: 22,982,400 (derived from 7,776,000 requests at 30% utilization, which implies a 100% capacity of 25,920,000, though the formula note specifically uses the relationship of 3 replicas to the throughput) - Calculation: (Total Cost of 3 Pods) / (Total Monthly Capacity in thousands of requests)Specifically, the formula 46 * 3 / 22,982.4 results in the rate of $0.006001. This ensures that while 3 replicas are run for redundancy, the cost is distributed across the total throughput provided by those pods.
A13: Base Platform (DTAP) | B13: Base Platform | C13: Fixed | D13: 4000 | E13: AKS, networking, APIM, Key Vault, ACR — Dev/Test/Acc/Prod
A14: Grafana | B14: Observability | C14: Fixed | D14: 500 | E14: Dashboards, alerting, metrics visualization
A15: Langfuse | B15: Observability | C15: Fixed | D15: 2799 | E15: Cloud Enterprise — base $2,499 + teams $300
A16: Langfuse (Usage) | B16: Usage based costs LF | C16: Per 1K LF Units | D16: 1104 | E16: $8.0/100K observations — tiered pricing at volume Langfuse (Usage)($0.08/1K x 13800.0K LF units)$1,104.00
A17: PostgreSQL (Azure Flexible Server HA) | B17: DB | C17: Fixed | D17: 750 | E17: General Purpose D4ds_v5, zone-redundant HA, 128 GB storage
A18: Redis | B18: Cache | C18: Fixed | D18: 320 | E18: Short term memory
A19: Platform Team | B19: TeamSubtotal: $10000.00 | C19: Fixed | D19: 11545 | E19: Shared platform engineering team costs (10000 eur) | 10 clients shoul break even | 100% agentic Team costs ~800k eur + 30% of the GC Team costs)
C21: Monthly | D21: =SUM(Table1[Costs]) -> 21434.687
C22: Annually | D22: =D21*12 -> 257216.25
H27: Master
H28: Node costs | I28: 140
H29: Pods per node | I29: 3 | J29: assuming we run 3 pods in one node (Conservative for large. microservice)
H30: Cost per pod | I30: =I28/I29 -> 46.666667
H31: base_pods = dev + stg + prod_min + dr = 1 + 2 + 3 + 1 = 7 pods | I31: 7 | J31: 1 dev 2 tst and stg, 3 for 3az in prod and 1 for DR reserved (base platform has also node capacity for DR)
H32: DTAP Base / agent = base_pods × cost_per_pod | I32: =I31*I28/3 -> 326.66667 | J32: the bare minmum a microservice compute will cost us to just "Exist" in dev test stg production .
H34: Consumpition based Compute
H35: RPS per pod in production | I35: 10
H36: Montly requests per pod (30%) | I36: =(I35* 86400 * 30 )*30% -> 7776000 | J36: Note: this means at 46 dollars a pod one pod can take 7.7 million requests a month. this means technically we add one more replica of pod per 7.7 million request coming to the pod.
H37: Autoscaling rate ($/1K requests) | I37: =I30*3/(I36*3/1000) -> 0.0060013717 | J37: we have to run 3 replicas (1 in each az for zone redundancies which gives us much higeher throughput in return anyway). so multiplying per pod costs by 3 and also possible throughput is times 3 as a gift. so rate remains the same. which every 1000 requests costs us this amount = 46*3/requestperpod/1000

Sheet WIP Simulations Platform
A2: Sessions | B2: Interactions | C2: Platform costs
A3: 600000 | B3: =A3*3 -> 1800000 | C3: 257216.25
A4: 5000000 | B4: =A4*3 -> 15000000

Sheet Margins
A1: Selling Price per interaction | C1: 0.07
A2: Platform Price | C2: 1000000
A3: Interactions in a session | C3: 3
A6: Sessions | B6: Interactions | C6: Revenue | D6: costs after discount for models to. microsoft | E6: Agentic Platform Compute + Team | F6: Kasisto | G6: Other Solutions | I6: Margin
A7: 600000 | B7: =A7*C3 -> 1800000 | C7: =C2 + (C1*C3*A7*12)+ (0.05*A7* 12) -> 2872000 | D7: =A7*Simulations!$K$2*3*12 -> 368004.06 | E7: 250000 | F7: 400000 | G7: 200000 | K7: =(C7-sum(D7:G7))/C7 -> 0.57590388
A8: 5000000 | B8: =A8*C3 -> 15000000 | C8: =C2+ (C1*C3*A8*12)+ (0.05*A8* 12) -> 16600000 | D8: =A8*Simulations!$K$2*3*12 -> 3066700.5 | E8: 1000000 | I8: =(C8-(D8+E8+F8))/C8 -> 0.75501804 | K8: =(C8-sum(D8:G8))/C8 -> 0.75501804

Sheet Instructions
A1: HOW TO USE
A3: 1. Fill in Use Cases sheet: A (name), B (app), C (model — must match Models sheet exactly), D (calls), E (input tokens), F (output tokens), K (monthly volume)
A4: 2. Columns G-H auto-lookup pricing from Models sheet
A5: 3. Columns I, J, L auto-calculate costs
A6: 4. Edit Models sheet to update pricing
